{
  "cart_id": "auto_0843",
  "items": [
    {
      "id": "C006",
      "price": 2873,
      "category": "衣服"
    },
    {
      "id": "H074",
      "price": 603,
      "category": "家電"
    },
    {
      "id": "O089",
      "price": 1427,
      "category": "其他"
    },
    {
      "id": "E040",
      "price": 2934,
      "category": "3C"
    },
    {
      "id": "O082",
      "price": 272,
      "category": "其他"
    },
    {
      "id": "O096",
      "price": 1445,
      "category": "其他"
    },
    {
      "id": "C008",
      "price": 442,
      "category": "衣服"
    },
    {
      "id": "H068",
      "price": 1052,
      "category": "家電"
    },
    {
      "id": "H075",
      "price": 2443,
      "category": "家電"
    },
    {
      "id": "C021",
      "price": 2689,
      "category": "衣服"
    },
    {
      "id": "E046",
      "price": 2137,
      "category": "3C"
    },
    {
      "id": "H079",
      "price": 1738,
      "category": "家電"
    },
    {
      "id": "E041",
      "price": 2272,
      "category": "3C"
    },
    {
      "id": "E034",
      "price": 1141,
      "category": "3C"
    },
    {
      "id": "E052",
      "price": 2839,
      "category": "3C"
    },
    {
      "id": "E042",
      "price": 2047,
      "category": "3C"
    },
    {
      "id": "C019",
      "price": 2833,
      "category": "衣服"
    },
    {
      "id": "H064",
      "price": 2331,
      "category": "家電"
    },
    {
      "id": "E044",
      "price": 642,
      "category": "3C"
    },
    {
      "id": "C028",
      "price": 1234,
      "category": "衣服"
    }
  ]
}