{
  "cart_id": "auto_0929",
  "items": [
    {
      "id": "O083",
      "price": 1210,
      "category": "其他"
    },
    {
      "id": "H066",
      "price": 1606,
      "category": "家電"
    },
    {
      "id": "H062",
      "price": 2397,
      "category": "家電"
    },
    {
      "id": "C001",
      "price": 2514,
      "category": "衣服"
    },
    {
      "id": "C006",
      "price": 2873,
      "category": "衣服"
    },
    {
      "id": "O091",
      "price": 2746,
      "category": "其他"
    },
    {
      "id": "C004",
      "price": 1519,
      "category": "衣服"
    },
    {
      "id": "H075",
      "price": 2443,
      "category": "家電"
    },
    {
      "id": "C027",
      "price": 467,
      "category": "衣服"
    },
    {
      "id": "C016",
      "price": 2176,
      "category": "衣服"
    },
    {
      "id": "C018",
      "price": 2768,
      "category": "衣服"
    },
    {
      "id": "H079",
      "price": 1738,
      "category": "家電"
    },
    {
      "id": "O096",
      "price": 1445,
      "category": "其他"
    },
    {
      "id": "C021",
      "price": 2689,
      "category": "衣服"
    },
    {
      "id": "C030",
      "price": 1739,
      "category": "衣服"
    },
    {
      "id": "C003",
      "price": 1266,
      "category": "衣服"
    },
    {
      "id": "C013",
      "price": 2508,
      "category": "衣服"
    },
    {
      "id": "E044",
      "price": 642,
      "category": "3C"
    },
    {
      "id": "E034",
      "price": 1141,
      "category": "3C"
    },
    {
      "id": "O089",
      "price": 1427,
      "category": "其他"
    }
  ]
}