{
  "cart_id": "targeted_0998",
  "items": [
    {
      "id": "C002",
      "price": 2036,
      "category": "衣服"
    },
    {
      "id": "C024",
      "price": 479,
      "category": "衣服"
    },
    {
      "id": "C015",
      "price": 621,
      "category": "衣服"
    },
    {
      "id": "H074",
      "price": 603,
      "category": "家電"
    },
    {
      "id": "H066",
      "price": 1606,
      "category": "家電"
    },
    {
      "id": "H078",
      "price": 2511,
      "category": "家電"
    },
    {
      "id": "C020",
      "price": 1421,
      "category": "衣服"
    },
    {
      "id": "C017",
      "price": 1182,
      "category": "衣服"
    },
    {
      "id": "H072",
      "price": 436,
      "category": "家電"
    },
    {
      "id": "E056",
      "price": 711,
      "category": "3C"
    },
    {
      "id": "E048",
      "price": 1761,
      "category": "3C"
    },
    {
      "id": "C019",
      "price": 2833,
      "category": "衣服"
    },
    {
      "id": "E049",
      "price": 322,
      "category": "3C"
    },
    {
      "id": "O095",
      "price": 2227,
      "category": "其他"
    },
    {
      "id": "H073",
      "price": 2649,
      "category": "家電"
    }
  ]
}