{
  "cart_id": "targeted_0211",
  "items": [
    {
      "id": "C019",
      "price": 2833,
      "category": "衣服"
    },
    {
      "id": "C027",
      "price": 467,
      "category": "衣服"
    },
    {
      "id": "O091",
      "price": 2746,
      "category": "其他"
    },
    {
      "id": "H063",
      "price": 2747,
      "category": "家電"
    },
    {
      "id": "E042",
      "price": 2047,
      "category": "3C"
    },
    {
      "id": "E050",
      "price": 1158,
      "category": "3C"
    },
    {
      "id": "C017",
      "price": 1182,
      "category": "衣服"
    },
    {
      "id": "O092",
      "price": 2408,
      "category": "其他"
    },
    {
      "id": "H080",
      "price": 1906,
      "category": "家電"
    },
    {
      "id": "E051",
      "price": 374,
      "category": "3C"
    },
    {
      "id": "C011",
      "price": 1767,
      "category": "衣服"
    }
  ]
}