{
  "cart_id": "targeted_0158",
  "items": [
    {
      "id": "E038",
      "price": 1722,
      "category": "3C"
    },
    {
      "id": "E037",
      "price": 338,
      "category": "3C"
    },
    {
      "id": "E056",
      "price": 711,
      "category": "3C"
    },
    {
      "id": "E050",
      "price": 1158,
      "category": "3C"
    },
    {
      "id": "C024",
      "price": 479,
      "category": "衣服"
    },
    {
      "id": "C001",
      "price": 2514,
      "category": "衣服"
    },
    {
      "id": "C021",
      "price": 2689,
      "category": "衣服"
    },
    {
      "id": "H078",
      "price": 2511,
      "category": "家電"
    },
    {
      "id": "C006",
      "price": 2873,
      "category": "衣服"
    },
    {
      "id": "E055",
      "price": 1462,
      "category": "3C"
    },
    {
      "id": "C008",
      "price": 442,
      "category": "衣服"
    },
    {
      "id": "E058",
      "price": 491,
      "category": "3C"
    },
    {
      "id": "O095",
      "price": 2227,
      "category": "其他"
    },
    {
      "id": "O097",
      "price": 1448,
      "category": "其他"
    }
  ]
}