{
  "cart_id": "targeted_0111",
  "items": [
    {
      "id": "C021",
      "price": 2689,
      "category": "衣服"
    },
    {
      "id": "C005",
      "price": 425,
      "category": "衣服"
    },
    {
      "id": "H073",
      "price": 2649,
      "category": "家電"
    },
    {
      "id": "H063",
      "price": 2747,
      "category": "家電"
    },
    {
      "id": "O098",
      "price": 530,
      "category": "其他"
    },
    {
      "id": "E051",
      "price": 374,
      "category": "3C"
    },
    {
      "id": "C008",
      "price": 442,
      "category": "衣服"
    },
    {
      "id": "O085",
      "price": 2479,
      "category": "其他"
    },
    {
      "id": "E054",
      "price": 474,
      "category": "3C"
    },
    {
      "id": "E058",
      "price": 491,
      "category": "3C"
    },
    {
      "id": "E045",
      "price": 1711,
      "category": "3C"
    }
  ]
}